setup.py
dj_kits/__init__.py
dj_kits/context_processors.py
dj_kits/middleware.py
dj_kits/models.py
dj_kits/storage.py
dj_kits.egg-info/PKG-INFO
dj_kits.egg-info/SOURCES.txt
dj_kits.egg-info/dependency_links.txt
dj_kits.egg-info/requires.txt
dj_kits.egg-info/top_level.txt
dj_kits.egg-info/zip-safe
dj_kits/autocomplete_light/__init__.py
dj_kits/decorators/__init__.py
dj_kits/magicpages/__init__.py
dj_kits/magicpages/urls.py
dj_kits/magicpages/views.py
dj_kits/templatetags/__init__.py
dj_kits/templatetags/dj_kit_tags.py
dj_kits/utils/__init__.py
dj_kits/utils/conf.py
dj_kits/utils/filters.py
dj_kits/utils/forms.py
dj_kits/utils/html.py
dj_kits/utils/logger.py
dj_kits/utils/queue.py
dj_kits/utils/templates.py
dj_kits/utils/timesince.py
dj_kits/utils/urls.py